ckandf-0.5-py3.8-nspkg.pth
ckandf/cli.py
ckandf-0.5.dist-info/LICENSE.txt
ckandf-0.5.dist-info/METADATA
ckandf-0.5.dist-info/WHEEL
ckandf-0.5.dist-info/entry_points.txt
ckandf-0.5.dist-info/namespace_packages.txt
ckandf-0.5.dist-info/top_level.txt
ckandf-0.5.dist-info/RECORD
